libfunbox/__init__.py
libfunbox/datatypes.py
libfunbox-1.9.dist-info/LICENCE
libfunbox-1.9.dist-info/METADATA
libfunbox-1.9.dist-info/WHEEL
libfunbox-1.9.dist-info/top_level.txt
libfunbox-1.9.dist-info/RECORD
