Metadata-Version: 2.1
Name: libfunbox
Version: 1.9
Summary: Orange Funbox 2.0 Wrapper
Home-page: https://flerken.zapto.org:1115/kuba/libfunbox
Author: kuba201
Project-URL: Source, https://flerken.zapto.org:1115/kuba/libfunbox
Keywords: orange,router,funbox
Classifier: Programming Language :: Python :: 3 :: Only
Classifier: License :: OSI Approved :: GNU General Public License (GPL)
License-File: LICENCE
Requires-Dist: requests
